task2-serial-transceiver/task2-2-fsm-sim/dual_layer_fsm.v
// =============================================================
//  dual_layer_fsm.v
//  任务2-2：双层状态机
//  ---------------------------------------------------------
//  功能：实现"顶层事务调度 + 底层命令执行"的双层 FSM，并完成收发仲裁
//    顶层：IDLE → LATCH_RX → START_SUB → WAIT_SUB → SEND_ACK → DONE
//          IDLE → SEND_REQ → DONE
//    底层：IDLE → APPLY → HOLD → DONE
//  握手：sub_start（顶层→底层）、sub_done（底层→顶层）
//  命令：'0'=全灭 '1'=红 '2'=绿 '3'=蓝 'A'/'a'=白
//  仲裁：rx_ready 优先于外部 req；忙碌期间用 1 字节 pending 缓冲避免丢字节
// =============================================================
module dual_layer_fsm (
    input  wire       clk,
    input  wire       rst_n,

    // 来自 UART_rx 的接收结果
    input  wire       rx_ready,     // 接收到一个完整字节时拉高1个clk
    input  wire [7:0] rx_data,      // 接收到的数据

    // 来自 UART_tx 的忙标志
    input  wire       tx_busy,      // 1表示正在发送，0表示空闲

    // 外部发送请求，例如 K1 手动发送 0x55
    input  wire       req,          // 外部请求，低优先级
    input  wire [7:0] req_data,     // 外部请求要发送的数据

    // 发给 UART_tx 的请求
    output reg        tx_start,     // 拉高1个clk，请求发送
    output reg [7:0]  tx_data,      // 要发送的数据

    // LED 模式输出
    output reg [2:0]  led_mode,

    // 调试观察用
    output reg [2:0]  top_state_dbg,
    output reg [1:0]  sub_state_dbg,
    output reg        cmd_valid_dbg
);

    // =====================================================
    // 顶层 FSM 状态定义
    // =====================================================
    localparam [2:0] TOP_IDLE      = 3'd0;
    localparam [2:0] TOP_LATCH_RX  = 3'd1;
    localparam [2:0] TOP_START_SUB = 3'd2;
    localparam [2:0] TOP_WAIT_SUB  = 3'd3;
    localparam [2:0] TOP_SEND_ACK  = 3'd4;
    localparam [2:0] TOP_SEND_REQ  = 3'd5;
    localparam [2:0] TOP_DONE      = 3'd6;

    // =====================================================
    // 底层 FSM 状态定义
    // =====================================================
    localparam [1:0] SUB_IDLE  = 2'd0;
    localparam [1:0] SUB_APPLY = 2'd1;
    localparam [1:0] SUB_HOLD  = 2'd2;
    localparam [1:0] SUB_DONE  = 2'd3;

    reg [2:0] top_state;
    reg [1:0] sub_state;

    reg [7:0] cmd_reg;
    reg       cmd_valid;
    reg       rx_pending_valid;
    reg [7:0] rx_pending_data;

    reg       sub_start;
    reg       sub_done;

    reg [3:0] hold_cnt;

    // =====================================================
    // 命令合法性判断
    // 0：全灭   1：红灯   2：绿灯   3：蓝灯   A/a：白灯
    // =====================================================
    wire cmd_reg_valid =
        (cmd_reg == 8'h30) ||  // '0'
        (cmd_reg == 8'h31) ||  // '1'
        (cmd_reg == 8'h32) ||  // '2'
        (cmd_reg == 8'h33) ||  // '3'
        (cmd_reg == 8'h41) ||  // 'A'
        (cmd_reg == 8'h61);    // 'a'

    // =====================================================
    // 顶层 FSM
    // =====================================================
    always @(posedge clk or negedge rst_n) begin
        if (!rst_n) begin
            top_state <= TOP_IDLE;
            cmd_reg   <= 8'h00;
            cmd_valid <= 1'b0;
            rx_pending_valid <= 1'b0;
            rx_pending_data  <= 8'h00;
            sub_start <= 1'b0;
            tx_start  <= 1'b0;
            tx_data   <= 8'h00;
        end else begin
            sub_start <= 1'b0;
            tx_start  <= 1'b0;

            if (rx_ready &&
                top_state != TOP_IDLE &&
                top_state != TOP_SEND_REQ &&
                !rx_pending_valid) begin
                rx_pending_valid <= 1'b1;
                rx_pending_data  <= rx_data;
            end

            case (top_state)
                TOP_IDLE: begin
                    cmd_valid <= 1'b0;
                    if (rx_pending_valid) begin
                        cmd_reg          <= rx_pending_data;
                        rx_pending_valid <= 1'b0;
                        top_state        <= TOP_LATCH_RX;
                    end else if (rx_ready) begin
                        cmd_reg   <= rx_data;
                        top_state <= TOP_LATCH_RX;
                    end else if (req) begin
                        cmd_reg   <= req_data;
                        top_state <= TOP_SEND_REQ;
                    end
                end

                TOP_LATCH_RX: begin
                    if (cmd_reg_valid) begin
                        cmd_valid <= 1'b1;
                        top_state <= TOP_START_SUB;
                    end else begin
                        cmd_valid <= 1'b0;
                        top_state <= TOP_IDLE;
                    end
                end

                TOP_START_SUB: begin
                    sub_start <= 1'b1;
                    top_state <= TOP_WAIT_SUB;
                end

                TOP_WAIT_SUB: begin
                    if (sub_done)
                        top_state <= TOP_SEND_ACK;
                end

                TOP_SEND_ACK: begin
                    if (!tx_busy) begin
                        tx_data   <= cmd_reg;
                        tx_start  <= 1'b1;
                        top_state <= TOP_DONE;
                    end
                end

                TOP_SEND_REQ: begin
                    if (rx_ready) begin
                        cmd_reg   <= rx_data;
                        top_state <= TOP_LATCH_RX;
                    end else if (!tx_busy) begin
                        tx_data   <= cmd_reg;
                        tx_start  <= 1'b1;
                        top_state <= TOP_DONE;
                    end
                end

                TOP_DONE: begin
                    top_state <= TOP_IDLE;
                end

                default: begin
                    top_state <= TOP_IDLE;
                end
            endcase
        end
    end

    // =====================================================
    // 底层 FSM
    // =====================================================
    always @(posedge clk or negedge rst_n) begin
        if (!rst_n) begin
            sub_state <= SUB_IDLE;
            led_mode  <= 3'd0;
            sub_done  <= 1'b0;
            hold_cnt  <= 4'd0;
        end else begin
            sub_done <= 1'b0;

            case (sub_state)
                SUB_IDLE: begin
                    hold_cnt <= 4'd0;
                    if (sub_start)
                        sub_state <= SUB_APPLY;
                end

                SUB_APPLY: begin
                    case (cmd_reg)
                        8'h30: led_mode <= 3'd0;
                        8'h31: led_mode <= 3'd1;
                        8'h32: led_mode <= 3'd2;
                        8'h33: led_mode <= 3'd3;
                        8'h41: led_mode <= 3'd4;
                        8'h61: led_mode <= 3'd4;
                        default: led_mode <= led_mode;
                    endcase
                    sub_state <= SUB_HOLD;
                end

                SUB_HOLD: begin
                    if (hold_cnt >= 4'd5) begin
                        hold_cnt  <= 4'd0;
                        sub_state <= SUB_DONE;
                    end else begin
                        hold_cnt <= hold_cnt + 4'd1;
                    end
                end

                SUB_DONE: begin
                    sub_done  <= 1'b1;
                    sub_state <= SUB_IDLE;
                end

                default: begin
                    sub_state <= SUB_IDLE;
                end
            endcase
        end
    end

    // 调试输出
    always @(*) begin
        top_state_dbg = top_state;
        sub_state_dbg = sub_state;
        cmd_valid_dbg = cmd_valid;
    end

endmodule

task2-serial-transceiver/task2-2-fsm-sim/tb_dual_layer_fsm.v
// =============================================================
//  tb_dual_layer_fsm.v
//  任务2-2：双层状态机 Testbench
//  ---------------------------------------------------------
//  测试场景：
//    1. 合法命令 '1' → led_mode=1, 回传 '1'
//    2. 非法命令 'X' → 忽略，led_mode 不变
//    3. 合法命令 'A' + tx_busy → 等待空闲后回传
//    4. 合法命令 '0' → led_mode=0
//    5. 合法命令 '2' → led_mode=2
//    6. rx_ready 与 req 同时到达 → 优先处理 rx_ready
//    7. K1 请求等待 tx_busy 时收到串口字节 → 串口接收抢占 K1
//    8. 上一条 ACK 等待 tx_busy 时收到下一字节 → pending 缓冲后继续处理
// =============================================================
`timescale 1ns/1ps

module tb_dual_layer_fsm;

    reg        clk;
    reg        rst_n;
    reg        rx_ready;
    reg [7:0]  rx_data;
    reg        tx_busy;
    reg        req;
    reg [7:0]  req_data;

    wire       tx_start;
    wire [7:0] tx_data;
    wire [2:0] led_mode;
    wire [2:0] top_state_dbg;
    wire [1:0] sub_state_dbg;
    wire       cmd_valid_dbg;

    integer errors;

    dual_layer_fsm dut (
        .clk           (clk),
        .rst_n         (rst_n),
        .rx_ready      (rx_ready),
        .rx_data       (rx_data),
        .tx_busy       (tx_busy),
        .req           (req),
        .req_data      (req_data),
        .tx_start      (tx_start),
        .tx_data       (tx_data),
        .led_mode      (led_mode),
        .top_state_dbg (top_state_dbg),
        .sub_state_dbg (sub_state_dbg),
        .cmd_valid_dbg (cmd_valid_dbg)
    );

    // 50MHz 时钟：周期 20ns
    initial begin
        clk = 1'b0;
        forever #10 clk = ~clk;
    end

    // 发送一个模拟 UART_rx 接收完成的字节
    task send_rx_byte;
        input [7:0] data;
        begin
            @(negedge clk);
            rx_data  <= data;
            rx_ready <= 1'b1;
            @(negedge clk);
            rx_ready <= 1'b0;
            rx_data  <= 8'h00;
        end
    endtask

    task expect_tx;
        input [7:0] expected;
        integer waited;
        begin
            waited = 0;
            while (tx_start) begin
                @(posedge clk);
            end

            while (!tx_start && waited < 100) begin
                @(posedge clk);
                waited = waited + 1;
            end
            if (!tx_start) begin
                $display("[ERROR] timeout waiting tx_start, expected 0x%02h", expected);
                errors = errors + 1;
            end else if (tx_data !== expected) begin
                $display("[ERROR] expected tx_data=0x%02h, got 0x%02h", expected, tx_data);
                errors = errors + 1;
            end else begin
                $display("[PASS] tx_data=0x%02h", tx_data);
            end
        end
    endtask

    task expect_led;
        input [2:0] expected;
        begin
            if (led_mode !== expected) begin
                $display("[ERROR] expected led_mode=%0d, got %0d", expected, led_mode);
                errors = errors + 1;
            end else begin
                $display("[PASS] led_mode=%0d", led_mode);
            end
        end
    endtask

    // 模拟 UART_tx 繁忙
    task make_tx_busy;
        input integer cycles;
        integer i;
        begin
            tx_busy <= 1'b1;
            for (i = 0; i < cycles; i = i + 1)
                @(posedge clk);
            tx_busy <= 1'b0;
        end
    endtask

    initial begin
        rst_n    = 1'b0;
        rx_ready = 1'b0;
        rx_data  = 8'h00;
        tx_busy  = 1'b0;
        req      = 1'b0;
        req_data = 8'h55;
        errors   = 0;

        #100;
        rst_n = 1'b1;
        repeat (5) @(posedge clk);

        // 测试1：合法命令 '1' -> led_mode=1, 回传 '1'
        send_rx_byte(8'h31);
        expect_tx(8'h31);
        expect_led(3'd1);

        // 测试2：非法命令 'X' -> 忽略
        send_rx_byte(8'h58);
        repeat (30) @(posedge clk);
        expect_led(3'd1);

        // 测试3：合法命令 'A' + tx_busy
        tx_busy <= 1'b1;
        send_rx_byte(8'h41);
        repeat (10) @(posedge clk);
        tx_busy <= 1'b0;
        expect_tx(8'h41);
        expect_led(3'd4);

        // 测试4：合法命令 '0' -> led_mode=0
        send_rx_byte(8'h30);
        expect_tx(8'h30);
        expect_led(3'd0);

        // 测试5：合法命令 '2' -> led_mode=2
        send_rx_byte(8'h32);
        expect_tx(8'h32);
        expect_led(3'd2);

        // 测试6：rx_ready 与 req 同时到达，接收优先，应该回传 '3' 而不是 'U'
        @(negedge clk);
        rx_data  <= 8'h33;
        rx_ready <= 1'b1;
        req      <= 1'b1;
        req_data <= 8'h55;
        @(negedge clk);
        rx_ready <= 1'b0;
        req      <= 1'b0;
        rx_data  <= 8'h00;
        expect_tx(8'h33);
        expect_led(3'd3);

        // 测试7：K1 请求已进入 SEND_REQ，但 tx_busy 期间收到 RX，应抢占 K1
        tx_busy <= 1'b1;
        @(negedge clk);
        req      <= 1'b1;
        req_data <= 8'h55;
        @(negedge clk);
        req <= 1'b0;
        repeat (2) @(posedge clk);
        send_rx_byte(8'h41);
        repeat (4) @(posedge clk);
        tx_busy <= 1'b0;
        expect_tx(8'h41);
        expect_led(3'd4);

        // 测试8：上一条 ACK 等待 tx_busy 时收到下一字节，应先回传旧字节，再处理 pending
        tx_busy <= 1'b1;
        send_rx_byte(8'h31);
        repeat (10) @(posedge clk);
        send_rx_byte(8'h32);
        repeat (4) @(posedge clk);
        tx_busy <= 1'b0;
        expect_tx(8'h31);
        expect_led(3'd1);
        expect_tx(8'h32);
        expect_led(3'd2);

        if (errors == 0)
            $display("\n=== ALL FSM TESTS PASSED ===");
        else
            $display("\n=== %0d FSM ERRORS FOUND ===", errors);

        $finish;
    end

endmodule

task2-serial-transceiver/task2-2-fsm-sim/exports/task2_fsm_modelsim_original.vcd
$date
	Mon May 18 13:23:13 2026
$end
$version
	ModelSim Version 2020.4
$end
$timescale
	1ps
$end

$scope module tb_dual_layer_fsm $end
$var reg 1 ! clk $end
$var reg 1 " rst_n $end
$var reg 1 # rx_ready $end
$var reg 8 $ rx_data [7:0] $end
$var reg 1 % tx_busy $end
$var reg 1 & req $end
$var reg 8 ' req_data [7:0] $end
$var wire 1 ( tx_start $end
$var wire 1 ) tx_data [7] $end
$var wire 1 * tx_data [6] $end
$var wire 1 + tx_data [5] $end
$var wire 1 , tx_data [4] $end
$var wire 1 - tx_data [3] $end
$var wire 1 . tx_data [2] $end
$var wire 1 / tx_data [1] $end
$var wire 1 0 tx_data [0] $end
$var wire 1 1 led_mode [2] $end
$var wire 1 2 led_mode [1] $end
$var wire 1 3 led_mode [0] $end
$var wire 1 4 top_state_dbg [2] $end
$var wire 1 5 top_state_dbg [1] $end
$var wire 1 6 top_state_dbg [0] $end
$var wire 1 7 sub_state_dbg [1] $end
$var wire 1 8 sub_state_dbg [0] $end
$var wire 1 9 cmd_valid_dbg $end
$var integer 32 : errors $end

$scope task send_rx_byte $end
$var reg 8 ; data [7:0] $end
$upscope $end

$scope task expect_tx $end
$var reg 8 < expected [7:0] $end
$var integer 32 = waited $end
$upscope $end

$scope task expect_led $end
$var reg 3 > expected [2:0] $end
$upscope $end

$scope task make_tx_busy $end
$var integer 32 ? cycles $end
$var integer 32 @ i $end
$upscope $end

$scope module dut $end
$var parameter 3 A TOP_IDLE $end
$var parameter 3 B TOP_LATCH_RX $end
$var parameter 3 C TOP_START_SUB $end
$var parameter 3 D TOP_WAIT_SUB $end
$var parameter 3 E TOP_SEND_ACK $end
$var parameter 3 F TOP_SEND_REQ $end
$var parameter 3 G TOP_DONE $end
$var parameter 2 H SUB_IDLE $end
$var parameter 2 I SUB_APPLY $end
$var parameter 2 J SUB_HOLD $end
$var parameter 2 K SUB_DONE $end
$var wire 1 L clk $end
$var wire 1 M rst_n $end
$var wire 1 N rx_ready $end
$var wire 1 O rx_data [7] $end
$var wire 1 P rx_data [6] $end
$var wire 1 Q rx_data [5] $end
$var wire 1 R rx_data [4] $end
$var wire 1 S rx_data [3] $end
$var wire 1 T rx_data [2] $end
$var wire 1 U rx_data [1] $end
$var wire 1 V rx_data [0] $end
$var wire 1 W tx_busy $end
$var wire 1 X req $end
$var wire 1 Y req_data [7] $end
$var wire 1 Z req_data [6] $end
$var wire 1 [ req_data [5] $end
$var wire 1 \ req_data [4] $end
$var wire 1 ] req_data [3] $end
$var wire 1 ^ req_data [2] $end
$var wire 1 _ req_data [1] $end
$var wire 1 ` req_data [0] $end
$var reg 1 a tx_start $end
$var reg 8 b tx_data [7:0] $end
$var reg 3 c led_mode [2:0] $end
$var reg 3 d top_state_dbg [2:0] $end
$var reg 2 e sub_state_dbg [1:0] $end
$var reg 1 f cmd_valid_dbg $end
$var reg 3 g top_state [2:0] $end
$var reg 2 h sub_state [1:0] $end
$var reg 8 i cmd_reg [7:0] $end
$var reg 1 j cmd_valid $end
$var reg 1 k rx_pending_valid $end
$var reg 8 l rx_pending_data [7:0] $end
$var reg 1 m sub_start $end
$var reg 1 n sub_done $end
$var reg 4 o hold_cnt [3:0] $end
$var wire 1 p cmd_reg_valid $end
$upscope $end
$upscope $end
$enddefinitions $end
#0
$dumpvars
0!
0"
0#
b0 $
0%
0&
b1010101 '
0a
b0 b
b0 c
b0 d
b0 e
0f
b0 g
b0 h
b0 i
0j
0k
b0 l
0m
0n
b0 o
bx ;
bx <
bx >
b0 A
b1 B
b10 C
b11 D
b100 E
b101 F
b110 G
b0 H
b1 I
b10 J
b11 K
b0 :
bx =
bx ?
bx @
0(
00
0/
0.
0-
0,
0+
0*
0)
03
02
01
06
05
04
08
07
09
0p
1`
0_
1^
0]
1\
0[
1Z
0Y
0X
0W
0V
0U
0T
0S
0R
0Q
0P
0O
0N
0M
0L
$end
#10000
1!
1L
#20000
0!
0L
#30000
1!
1L
#40000
0!
0L
#50000
1!
1L
#60000
0!
0L
#70000
1!
1L
#80000
0!
0L
#90000
1!
1L
#100000
1"
0!
1M
0L
#110000
1!
1L
#120000
0!
0L
#130000
1!
1L
#140000
0!
0L
#150000
1!
1L
#160000
0!
0L
#170000
1!
1L
#180000
0!
0L
#190000
1!
1L
b110001 ;
#200000
0!
0L
b110001 $
1#
1V
1R
1Q
1N
#210000
1!
1L
b110001 i
b1 g
1p
b1 d
16
#220000
0!
0L
b110001 <
b0 =
0#
b0 $
0N
0V
0R
0Q
#230000
1!
1L
b1 =
1j
b10 g
b10 d
1f
06
15
19
#240000
0!
0L
#250000
1!
1L
b10 =
1m
b11 g
b11 d
16
#260000
0!
0L
#270000
1!
1L
b11 =
0m
b1 h
b1 e
18
#280000
0!
0L
#290000
1!
1L
b100 =
b1 c
b10 h
13
b10 e
08
17
#300000
0!
0L
#310000
1!
1L
b101 =
b1 o
#320000
0!
0L
#330000
1!
1L
b110 =
b10 o
#340000
0!
0L
#350000
1!
1L
b111 =
b11 o
#360000
0!
0L
#370000
1!
1L
b1000 =
b100 o
#380000
0!
0L
#390000
1!
1L
b1001 =
b101 o
#400000
0!
0L
#410000
1!
1L
b1010 =
b0 o
b11 h
b11 e
18
#420000
0!
0L
#430000
1!
1L
b1011 =
1n
b0 h
b0 e
08
07
#440000
0!
0L
#450000
1!
1L
b1100 =
b100 g
0n
b100 d
06
05
14
#460000
0!
0L
#470000
1!
1L
b1101 =
b110001 b
1a
b110 g
10
1,
1+
1(
b110 d
15
#480000
0!
0L
#490000
1!
1L
b1110 =
b1 >
b1011000 ;
0a
b0 g
0(
b0 d
05
04
#500000
0!
0L
b1011000 $
1#
1S
1R
1P
1N
#510000
1!
1L
0j
b1011000 i
b1 g
0p
b1 d
0f
16
09
#520000
0!
0L
0#
b0 $
0N
0S
0R
0P
#530000
1!
1L
b0 g
b0 d
06
